chargerbuzzfall2025/__init__.py
chargerbuzzfall2025/model/__init__.py
chargerbuzzfall2025/model/neuralnet.py
chargerbuzzfall2025/model/regression.py
chargerbuzzfall2025/py.typed
chargerbuzzfall2025-0.1.0.dist-info/WHEEL
chargerbuzzfall2025-0.1.0.dist-info/METADATA
chargerbuzzfall2025-0.1.0.dist-info/RECORD
