Metadata-Version: 2.3
Name: chargerbuzzfall2025
Version: 0.1.0
Summary: Add your description here
Author: sazzad1008
Author-email: sazzad1008 <sazzadhossen100@gmail.com>
Requires-Dist: matplotlib>=3.10.7
Requires-Dist: numpy>=2.3.5
Requires-Dist: onnx>=1.20.0
Requires-Dist: onnxruntime>=1.23.2
Requires-Dist: pandas>=2.3.3
Requires-Dist: scikit-learn>=1.7.2
Requires-Dist: seaborn>=0.13.2
Requires-Dist: torch>=2.9.1
Requires-Python: >=3.12
